searchpass/VERSION.txt
searchpass/__info__.py
searchpass/__init__.py
searchpass/__main__.py
searchpass/db/__init__.py
searchpass/db/lexer.py
searchpass/db/searchpass.db
searchpass/db/sql.py
searchpass/db/table.py
searchpass-2.0.1.dist-info/LICENSE
searchpass-2.0.1.dist-info/METADATA
searchpass-2.0.1.dist-info/WHEEL
searchpass-2.0.1.dist-info/entry_points.txt
searchpass-2.0.1.dist-info/top_level.txt
searchpass-2.0.1.dist-info/RECORD
