Metadata-Version: 2.1
Name: searchpass
Version: 2.0.1
Summary: Default passwords search tool supporting many open source databases
Author-email: Alexandre D'Hondt <alexandre.dhondt@gmail.com>
License: GNU GENERAL PUBLIC LICENSE
Project-URL: homepage, https://github.com/dhondta/searchpass
Project-URL: issues, https://github.com/dhondta/searchpass/issues
Project-URL: repository, https://github.com/dhondta/searchpass
Keywords: default-passwords,default-credentials,network-devices,search-tool,pentest-tool,cybersecurity-tool
Classifier: Development Status :: 5 - Production/Stable
Classifier: Environment :: Console
Classifier: Intended Audience :: Developers
Classifier: Intended Audience :: Information Technology
Classifier: Intended Audience :: Other Audience
Classifier: License :: OSI Approved :: GNU General Public License v3 or later (GPLv3+)
Classifier: Programming Language :: Python :: 3
Classifier: Programming Language :: Python :: 3.8
Classifier: Programming Language :: Python :: 3.9
Classifier: Programming Language :: Python :: 3.10
Classifier: Programming Language :: Python :: 3.11
Classifier: Programming Language :: Python :: 3.12
Classifier: Topic :: Software Development :: Libraries :: Python Modules
Classifier: Topic :: Security
Requires-Python: <4,>=3.8
License-File: LICENSE
Requires-Dist: pybots >=2.1.5
Requires-Dist: zipp >=3.19.1
